barstow/__init__.py
barstow/dataset.py
barstow/io.py
barstow/partitioning.py
barstow/py.typed
barstow/stowage.py
barstow-0.2.7.dist-info/WHEEL
barstow-0.2.7.dist-info/METADATA
barstow-0.2.7.dist-info/RECORD
