Metadata-Version: 2.1
Name: barstow
Version: 0.2.7
Summary: Library for managing Arrow datasets
Author: Mat Leonard
Author-email: leonard.mat@gmail.com
Requires-Python: >=3.7.1,<4
Classifier: Programming Language :: Python :: 3
Classifier: Programming Language :: Python :: 3.10
Classifier: Programming Language :: Python :: 3.8
Classifier: Programming Language :: Python :: 3.9
Requires-Dist: pandas (>=1.3.1)
Requires-Dist: pyarrow (>=9.0.0,<10.0.0)
